pyharmonytools/Cm - possible_fingerings.txt
pyharmonytools/Cmaj7 - possible_fingerings.txt
pyharmonytools/D - possible_fingerings.txt
pyharmonytools/__init__.py
pyharmonytools/chord_sequence_search.py
pyharmonytools/generate_possible_chords.py
pyharmonytools/harmony_runner.py
pyharmonytools/tab2chords.py
pyharmonytools/displays/__init__.py
pyharmonytools/displays/console.py
pyharmonytools/displays/console_for_guitar_neck.py
pyharmonytools/displays/console_for_guitar_tab.py
pyharmonytools/displays/unit_test_report.py
pyharmonytools/guitar/__init__.py
pyharmonytools/guitar/guitar_neck/__init__.py
pyharmonytools/guitar/guitar_neck/fingering.py
pyharmonytools/guitar/guitar_neck/neck.py
pyharmonytools/guitar/guitar_neck/neck_exception.py
pyharmonytools/guitar/guitar_tab/__init__.py
pyharmonytools/guitar/guitar_tab/chord_and_fingering.py
pyharmonytools/guitar/guitar_tab/guitar_tab.py
pyharmonytools/guitar/guitar_tab/note_fret_caret.py
pyharmonytools/guitar/guitar_tab/string_and_cell.py
pyharmonytools/harmony/__init__.py
pyharmonytools/harmony/cadence.py
pyharmonytools/harmony/circle_of_5th.py
pyharmonytools/harmony/cof_chord.py
pyharmonytools/harmony/degree.py
pyharmonytools/harmony/note.py
pyharmonytools/song/__init__.py
pyharmonytools/song/song.py
pyharmonytools/song/text_song.py
pyharmonytools/song/ultimate_guitar_capture.py
pyharmonytools/song/ultimate_guitar_search.py
pyharmonytools/song/ultimate_guitar_song.py
test/__init__.py
test/0_mocked_tests/__init__.py
test/0_mocked_tests/test_guitar_tab_mocked.py
test/0_mocked_tests/test_note.py
test/1_objects_tests/__init__.py
test/1_objects_tests/test_cadence.py
test/1_objects_tests/test_circle_of_5th.py
test/1_objects_tests/test_cof_chord.py
test/1_objects_tests/test_console_for_guitar_neck.py
test/1_objects_tests/test_degree.py
test/1_objects_tests/test_fingering.py
test/1_objects_tests/test_guitar_tab.py
test/1_objects_tests/test_harmony_tools.py
test/1_objects_tests/test_neck.py
test/1_objects_tests/test_text_song.py
pyHarmonyTooling-0.10.0.dist-info/LICENSE
pyHarmonyTooling-0.10.0.dist-info/METADATA
pyHarmonyTooling-0.10.0.dist-info/WHEEL
pyHarmonyTooling-0.10.0.dist-info/top_level.txt
pyHarmonyTooling-0.10.0.dist-info/RECORD
