Metadata-Version: 2.1
Name: pyHarmonyTooling
Version: 0.10.0
Summary: Series of tools to handle harmony in music
Home-page: https://github.com/Moustov/pyharmonytooling
Author: Christophe Moustier
License: BSD 3-Clause License
Keywords: music,guitar,chords,circle of 5th
Classifier: Programming Language :: Python :: 3.9
Classifier: Development Status :: 3 - Alpha
Classifier: Environment :: Console
Classifier: Intended Audience :: Developers
Classifier: Intended Audience :: Education
Classifier: Natural Language :: English
Classifier: Topic :: Artistic Software
Classifier: Topic :: Education
Classifier: Topic :: Games/Entertainment
Classifier: Topic :: Multimedia :: Sound/Audio :: Analysis
Classifier: Topic :: Text Processing
Classifier: Topic :: Utilities
License-File: LICENSE
Requires-Dist: pychord (>=1.1.0)
Requires-Dist: deepdiff (>=6.2.1)
Requires-Dist: Google-Search-API (>=1.1.14)
